CHANGELOG.md
opencv_camcalib/__init__.py
opencv_camcalib/app.py
opencv_camcalib/cli.py
opencv_camcalib/core.py
opencv_camcalib/gui/__init__.py
opencv_camcalib/gui/chessboard_calibration.py
opencv_camcalib/gui/config.py
opencv_camcalib/gui/distortion_correction.py
opencv_camcalib/gui/screenshot_setting.py
opencv_camcalib/gui/ui/chessboard_calibration.py
opencv_camcalib/gui/ui/chessboard_calibration.ui
opencv_camcalib/gui/ui/distortion_correction.py
opencv_camcalib/gui/ui/distortion_correction.ui
opencv_camcalib/gui/ui/main_window.py
opencv_camcalib/gui/ui/main_window.ui
opencv_camcalib/gui/ui/screenshot_setting.py
opencv_camcalib/gui/ui/screenshot_setting.ui
opencv_camcalib/utils/gen_pattern.py
opencv_camcalib/utils/svgfig.py
opencv_camcalib-0.1.3.dist-info/entry_points.txt
opencv_camcalib-0.1.3.dist-info/LICENSE
opencv_camcalib-0.1.3.dist-info/WHEEL
opencv_camcalib-0.1.3.dist-info/METADATA
opencv_camcalib-0.1.3.dist-info/RECORD
