Metadata-Version: 2.1
Name: opencv-camcalib
Version: 0.1.3
Summary: 
Home-page: https://github.com/XavierJiezou/OpenCV-CamCalib
License: MIT
Keywords: python,opencv,camera,calibration
Author: XavierJiezou
Author-email: 878972272@qq.com
Requires-Python: >=3.7.2,<3.11
Classifier: License :: OSI Approved :: MIT License
Classifier: Programming Language :: Python :: 3
Classifier: Programming Language :: Python :: 3.10
Classifier: Programming Language :: Python :: 3.8
Classifier: Programming Language :: Python :: 3.9
Classifier: Topic :: Software Development :: Libraries :: Python Modules
Requires-Dist: fire (>=0.4.0,<0.5.0)
Requires-Dist: func-timeout (>=4.3.5,<5.0.0)
Requires-Dist: opencv-python (<=4.5.5.64)
Requires-Dist: rich (>=12.5.1,<13.0.0)
Project-URL: Documentation, https://github.com/XavierJiezou/OpenCV-CamCalib
Project-URL: Repository, https://github.com/XavierJiezou/OpenCV-CamCalib
